<?xml version="1.0" encoding="UTF-8"?>

<!DOCTYPE fontscolors PUBLIC "-//NetBeans//DTD Editor Fonts and Colors settings 1.1//EN" "http://www.netbeans.org/dtds/EditorFontsColors-1_1.dtd">
<fontscolors>
  <fontcolor name="number" default="number" />
  <fontcolor name="comment" default="comment" />
  <fontcolor name="string" default="string" />
  <fontcolor name="whitespace" default="whitespace" />

  <fontcolor name="method" default="keyword" />
  <fontcolor name="request_separator" default="comment">
    <font style="bold+italic" />
  </fontcolor>

  <fontcolor name="mod-method" default="method" />
  <fontcolor name="mod-field" default="field" />
  <fontcolor name="mod-custom1" default="string" />
</fontscolors>